svg/__init__.py
svg/transform/__init__.py
svg.transform-0.1b1.dist-info/LICENSE.txt
svg.transform-0.1b1.dist-info/METADATA
svg.transform-0.1b1.dist-info/WHEEL
svg.transform-0.1b1.dist-info/top_level.txt
svg.transform-0.1b1.dist-info/zip-safe
svg.transform-0.1b1.dist-info/RECORD
