Metadata-Version: 2.1
Name: svg.transform
Version: 0.1b1
Summary: SVG path objects and parser
Home-page: https://github.com/regebro/svg.transform
Author: Lennart Regebro
Author-email: regebro@gmail.com
License: MIT
Keywords: svg,path,maths,transforms
Platform: UNKNOWN
Classifier: Development Status :: 3 - Alpha
Classifier: Intended Audience :: Developers
Classifier: License :: OSI Approved :: MIT License
Classifier: Operating System :: OS Independent
Classifier: Programming Language :: Python
Classifier: Programming Language :: Python :: 3
Classifier: Programming Language :: Python :: 3.8
Classifier: Programming Language :: Python :: 3.9
Classifier: Programming Language :: Python :: 3.10
Classifier: Programming Language :: Python :: 3.11
Classifier: Programming Language :: Python :: 3 :: Only
Classifier: Programming Language :: Python :: Implementation :: PyPy
Classifier: Topic :: Multimedia :: Graphics
Requires-Python: >=3.8
License-File: LICENSE.txt
Requires-Dist: numpy
Provides-Extra: test
Requires-Dist: Pillow ; extra == 'test'
Requires-Dist: black ; extra == 'test'
Requires-Dist: check-manifest ; extra == 'test'
Requires-Dist: flake8 ; extra == 'test'
Requires-Dist: pyroma ; extra == 'test'
Requires-Dist: pytest ; extra == 'test'
Requires-Dist: pytest-cov ; extra == 'test'
Requires-Dist: zest.releaser[recommended] ; extra == 'test'
